subwinder/__init__.py
subwinder/_constants.py
subwinder/_internal_utils.py
subwinder/_request.py
subwinder/core.py
subwinder/exceptions.py
subwinder/info.py
subwinder/lang.py
subwinder/media.py
subwinder/ranking.py
subwinder/utils.py
subwinder-1.1.2.dist-info/LICENSE
subwinder-1.1.2.dist-info/WHEEL
subwinder-1.1.2.dist-info/METADATA
subwinder-1.1.2.dist-info/RECORD
