Metadata-Version: 2.1
Name: subwinder
Version: 1.1.2
Summary: An ergonomic python library for the opensubtitles.org API
Home-page: https://github.com/LovecraftianHorror/subwinder
License: AGPL-3.0
Keywords: subtitles,opensubtitles,subtitles api,movies,tv shows
Author: Lovecraftian Horror
Author-email: LovecraftianHorror@pm.me
Requires-Python: >=3.7,<4.0
Classifier: License :: OSI Approved :: GNU Affero General Public License v3
Classifier: Programming Language :: Python :: 3
Classifier: Programming Language :: Python :: 3.7
Classifier: Programming Language :: Python :: 3.8
Provides-Extra: atomic_downloads
Requires-Dist: atomicwrites (>=1.4,<2.0); extra == "atomic_downloads"
Project-URL: Repository, https://github.com/LovecraftianHorror/subwinder
